odoo9_addon_mail_improved_tracking_value-9.0.1.0.0.99.dev2-py2.7-nspkg.pth
odoo9_addon_mail_improved_tracking_value-9.0.1.0.0.99.dev2.dist-info/METADATA
odoo9_addon_mail_improved_tracking_value-9.0.1.0.0.99.dev2.dist-info/RECORD
odoo9_addon_mail_improved_tracking_value-9.0.1.0.0.99.dev2.dist-info/WHEEL
odoo9_addon_mail_improved_tracking_value-9.0.1.0.0.99.dev2.dist-info/namespace_packages.txt
odoo9_addon_mail_improved_tracking_value-9.0.1.0.0.99.dev2.dist-info/top_level.txt
odoo_addons/mail_improved_tracking_value/README.rst
odoo_addons/mail_improved_tracking_value/__init__.py
odoo_addons/mail_improved_tracking_value/__openerp__.py
odoo_addons/mail_improved_tracking_value/i18n/mail_improved_tracking_value.pot
odoo_addons/mail_improved_tracking_value/models/__init__.py
odoo_addons/mail_improved_tracking_value/models/mail_tracking_value.py
odoo_addons/mail_improved_tracking_value/static/description/icon.png
odoo_addons/mail_improved_tracking_value/tests/__init__.py
odoo_addons/mail_improved_tracking_value/tests/test_improved_tracking_value.py
odoo_addons/mail_improved_tracking_value/views/mail_tracking_value.xml
